mathco/__init__.py
mathco/basic.py
mathco-0.0.2.dist-info/LICENSE
mathco-0.0.2.dist-info/METADATA
mathco-0.0.2.dist-info/WHEEL
mathco-0.0.2.dist-info/top_level.txt
mathco-0.0.2.dist-info/RECORD
