Metadata-Version: 2.1
Name: mathco
Version: 0.0.2
Summary: Companion for your Mathematical operations
Home-page: https://github.com/AbelR007/Mathco
Author: Abel Roy
Author-email: abelroi007@gmail.com
License: UNKNOWN
Platform: UNKNOWN
Classifier: Programming Language :: Python :: 3
Classifier: License :: OSI Approved :: GNU Affero General Public License v3
Classifier: Operating System :: OS Independent
License-File: LICENSE
